s3_kvs.py
s3_kvs-0.1.3.dist-info/LICENSE.txt
s3_kvs-0.1.3.dist-info/WHEEL
s3_kvs-0.1.3.dist-info/METADATA
s3_kvs-0.1.3.dist-info/RECORD
