Metadata-Version: 2.1
Name: s3-kvs
Version: 0.1.3
Summary: Python wrapper for an AWS S3 backed key-value store.
Home-page: https://github.com/octavenz/s3-kvs
License: MIT
Author: Richard Campen
Author-email: richard@campen.co
Requires-Python: >=3.6,<4.0
Classifier: License :: OSI Approved :: MIT License
Classifier: Programming Language :: Python :: 3
Classifier: Programming Language :: Python :: 3.6
Classifier: Programming Language :: Python :: 3.7
Classifier: Programming Language :: Python :: 3.8
Requires-Dist: requests (>=2.23.0,<3.0.0)
